lab3/ex3/fulladder.v
module fulladder(a, b, ci, sum, co);
  input   a, b, ci;
  output  sum, co;

  assign sum = a^b^ci;
  assign co = (a&b) | (a&ci) | (b&ci);
endmodule

lab3/ex4/add4.v
`include "../ex3/fulladder.v"

module add4(a, b, ci, sum, co);

  input   [3:0] a, b;
  input   ci;
  output  [3:0] sum;
  output  co;
  wire     [3:0] citmp;
  
  assign citmp[0] = ci;
  fulladder fa0(a[0], b[0], citmp[0], sum[0], citmp[1]);
  fulladder fa1(a[1], b[1], citmp[1], sum[1], citmp[2]);
  fulladder fa2(a[2], b[2], citmp[2], sum[2], citmp[3]);
  fulladder fa3(a[3], b[3], citmp[3], sum[3], co);

endmodule

lab3/ex5/addsub.v
`include "../ex4/add4.v"

module	addsub( result, operand_a, operand_b, mode );

	input	[3:0]	operand_a, operand_b;
	input	mode;
	output	[3:0]	result;
	wire co;
	wire	[3:0]	operand_b_modified;

	add4	m1(
		.sum(result),
		.co(co),
		.a(operand_a),	 
		.b((mode) ? ~operand_b : operand_b),	
		.ci(mode)
	);	
endmodule

lab3/ex5/addsub_tb.v
module    addsub_tb;
    
    // for DUT port connection
    reg     mode;
    reg     [3:0] operand_a, operand_b;
    wire    [3:0] result;
    wire co;
    
    // for pattern generation
    integer a, b, expect, error_num;
    reg overflow;
    wire [3:0] expect_out = expect[3:0];    // compare "expect_out" with "result"

    addsub as(result, operand_a, operand_b, mode);
    assign co = overflow;

    // give stimulus pattern
    initial begin
    error_num = 0;

    $dumpfile("waves.vcd");
    $dumpvars;

    $display( "\nTest subtraction mode." );
    #10 mode = 1'b1;
    
    for( a=-8; a<=7; a=a+1 ) begin
        for( b=-8; b<=7; b=b+1 ) begin
            
            operand_a = a[3:0];
            operand_b = b[3:0];
            expect = a - b;
    
            #1;
            if( expect >= -8 && expect <= 7 ) begin
                overflow = 1'b0;
                if( expect[3:0] !== result ) begin
                    error_num = error_num + 1;
                    $display( "Error(%d):(%d)-(%d) Expect(%b) Output(%b)", error_num[9:0], a, b, expect[3:0], result );
                end
            end
            else begin
                overflow = 1'b1;
            end
    
            #1;
        end
    end

    $display( "\nTest addition mode." );
    mode = 1'b0;
    
    for( a=-8; a<=7; a=a+1 ) begin
        for( b=-8; b<=7; b=b+1 ) begin
            
            operand_a = a[3:0];
            operand_b = b[3:0];
            expect = a + b;
    
            #1;
            if( expect >= -8 && expect <= 7 ) begin
                overflow = 1'b0;
                if( expect[3:0] !== result ) begin
                    error_num = error_num + 1;
                    $display( "Error(%d):(%d)+(%d) Expect(%b) Output(%b)", error_num[9:0], a, b, expect[3:0], result );
                end
            end
            else begin
                overflow = 1'b1;
            end
    
            #1;
        end
    end
    
    if( error_num==0 )
        $display( "\nPass all test\n" );
    else
        $display( "\nFail, error number = %d\n", error_num );
    
    #10 $finish;
    end

endmodule

lab3/ex5/waves.vcd
$date
    Apr 11, 2018  16:21:46
$end
$version
    TOOL:	ncsim(64)	14.10-s021
$end
$timescale
    1 ns
$end

$scope module addsub_tb $end
$var reg       1 !    mode  $end
$var reg       4 "    operand_a [3:0] $end
$var reg       4 #    operand_b [3:0] $end
$var wire      1 $    result [3] $end
$var wire      1 %    result [2] $end
$var wire      1 &    result [1] $end
$var wire      1 '    result [0] $end
$var wire      1 (    co  $end
$var integer  32 )    a  $end
$var integer  32 *    b  $end
$var integer  32 +    expect  $end
$var integer  32 ,    error_num  $end
$var reg       1 -    overflow  $end
$var wire      4 .    expect_out [3:0] $end

$scope module as $end
$var wire      1 /    operand_a [3] $end
$var wire      1 0    operand_a [2] $end
$var wire      1 1    operand_a [1] $end
$var wire      1 2    operand_a [0] $end
$var wire      4 3    operand_b [3:0] $end
$var wire      1 4    mode  $end
$var wire      1 $    result [3] $end
$var wire      1 %    result [2] $end
$var wire      1 &    result [1] $end
$var wire      1 '    result [0] $end
$var wire      1 5    co  $end
$var wire      4 6    operand_b_modified [3:0] $end

$scope module m1 $end
$var wire      1 /    a [3] $end
$var wire      1 0    a [2] $end
$var wire      1 1    a [1] $end
$var wire      1 2    a [0] $end
$var wire      1 7    b [3] $end
$var wire      1 8    b [2] $end
$var wire      1 9    b [1] $end
$var wire      1 :    b [0] $end
$var wire      1 4    ci  $end
$var wire      1 $    sum [3] $end
$var wire      1 %    sum [2] $end
$var wire      1 &    sum [1] $end
$var wire      1 '    sum [0] $end
$var wire      1 5    co  $end
$var wire      1 ;    citmp [3] $end
$var wire      1 <    citmp [2] $end
$var wire      1 =    citmp [1] $end
$var wire      1 >    citmp [0] $end

$scope module fa0 $end
$var wire      1 2    a  $end
$var wire      1 :    b  $end
$var wire      1 >    ci  $end
$var wire      1 '    sum  $end
$var wire      1 =    co  $end
$upscope $end


$scope module fa1 $end
$var wire      1 1    a  $end
$var wire      1 9    b  $end
$var wire      1 =    ci  $end
$var wire      1 &    sum  $end
$var wire      1 <    co  $end
$upscope $end


$scope module fa2 $end
$var wire      1 0    a  $end
$var wire      1 8    b  $end
$var wire      1 <    ci  $end
$var wire      1 %    sum  $end
$var wire      1 ;    co  $end
$upscope $end


$scope module fa3 $end
$var wire      1 /    a  $end
$var wire      1 7    b  $end
$var wire      1 ;    ci  $end
$var wire      1 $    sum  $end
$var wire      1 5    co  $end
$upscope $end

$upscope $end

$upscope $end

$upscope $end

$enddefinitions $end
$dumpvars
x!
bx "
bx #
x$
x%
x&
x'
x(
bx )
bx *
bx +
b0 ,
x-
bx .
x/
x0
x1
x2
bx 3
x4
x5
bz 6
x7
x8
x9
x:
x;
x<
x=
x>
$end
#10
1!
b11111111111111111111111111111000 )
b11111111111111111111111111111000 *
b1000 "
b1000 #
b0 +
b0 .
b1000 3
1/
00
01
02
14
1>
07
18
19
1:
1=
0'
1<
0&
1;
0%
15
0$
#11
0-
0(
#12
b11111111111111111111111111111001 *
b1001 #
b11111111111111111111111111111111 +
b1111 .
b1001 3
0:
0=
1'
0<
1&
0;
1%
05
1$
#14
b11111111111111111111111111111010 *
b1010 #
b11111111111111111111111111111110 +
b1110 .
b1010 3
09
1:
1=
0'
#16
b11111111111111111111111111111011 *
b1011 #
b11111111111111111111111111111101 +
b1101 .
b1011 3
0:
0=
1'
0&
#18
b11111111111111111111111111111100 *
b1100 #
b11111111111111111111111111111100 +
b1100 .
b1100 3
08
19
1:
1=
0'
1%
1<
#20
b11111111111111111111111111111101 *
b1101 #
b11111111111111111111111111111011 +
b1011 .
b1101 3
0:
0=
1'
0<
1&
0%
#22
b11111111111111111111111111111110 *
b1110 #
b11111111111111111111111111111010 +
b1010 .
b1110 3
09
1:
1=
0'
#24
b11111111111111111111111111111111 *
b1111 #
b11111111111111111111111111111001 +
b1001 .
b1111 3
0:
0=
1'
0&
#26
b0 *
b0 #
b11111111111111111111111111111000 +
b1000 .
b0 3
17
18
19
1:
1=
0'
0%
15
1$
1<
1;
#28
b1 *
b1 #
b11111111111111111111111111110111 +
b111 .
b1 3
0:
0=
1'
0<
1&
0;
1%
0$
#29
1-
1(
#30
b10 *
b10 #
b11111111111111111111111111110110 +
b110 .
b10 3
09
1:
1=
0'
#32
b11 *
b11 #
b11111111111111111111111111110101 +
b101 .
b11 3
0:
0=
1'
0&
#34
b100 *
b100 #
b11111111111111111111111111110100 +
b100 .
b100 3
08
19
1:
1=
0'
1%
1<
#36
b101 *
b101 #
b11111111111111111111111111110011 +
b11 .
b101 3
0:
0=
1'
0<
1&
0%
#38
b110 *
b110 #
b11111111111111111111111111110010 +
b10 .
b110 3
09
1:
1=
0'
#40
b111 *
b111 #
b11111111111111111111111111110001 +
b1 .
b111 3
0:
0=
1'
0&
#42
b1000 *
b11111111111111111111111111111001 )
b11111111111111111111111111111000 *
b1001 "
b1000 #
b1 +
b1000 3
12
1=
0'
1&
07
18
19
1:
1'
1<
0&
15
0$
1;
#43
0-
0(
#44
b11111111111111111111111111111001 *
b1001 #
b0 +
b0 .
b1001 3
0:
0'
#46
b11111111111111111111111111111010 *
b1010 #
b11111111111111111111111111111111 +
b1111 .
b1010 3
09
1:
1'
0<
1&
0;
1%
05
1$
#48
b11111111111111111111111111111011 *
b1011 #
b11111111111111111111111111111110 +
b1110 .
b1011 3
0:
0'
#50
b11111111111111111111111111111100 *
b1100 #
b11111111111111111111111111111101 +
b1101 .
b1100 3
08
19
1:
1'
1<
0&
#52
b11111111111111111111111111111101 *
b1101 #
b11111111111111111111111111111100 +
b1100 .
b1101 3
0:
0'
#54
b11111111111111111111111111111110 *
b1110 #
b11111111111111111111111111111011 +
b1011 .
b1110 3
09
1:
1'
0<
1&
0%
#56
b11111111111111111111111111111111 *
b1111 #
b11111111111111111111111111111010 +
b1010 .
b1111 3
0:
0'
#58
b0 *
b0 #
b11111111111111111111111111111001 +
b1001 .
b0 3
17
18
19
1:
1'
1<
0&
15
1$
1;
#60
b1 *
b1 #
b11111111111111111111111111111000 +
b1000 .
b1 3
0:
0'
#62
b10 *
b10 #
b11111111111111111111111111110111 +
b111 .
b10 3
09
1:
1'
0<
1&
0;
1%
0$
#63
1-
1(
#64
b11 *
b11 #
b11111111111111111111111111110110 +
b110 .
b11 3
0:
0'
#66
b100 *
b100 #
b11111111111111111111111111110101 +
b101 .
b100 3
08
19
1:
1'
1<
0&
#68
b101 *
b101 #
b11111111111111111111111111110100 +
b100 .
b101 3
0:
0'
#70
b110 *
b110 #
b11111111111111111111111111110011 +
b11 .
b110 3
09
1:
1'
0<
1&
0%
#72
b111 *
b111 #
b11111111111111111111111111110010 +
b10 .
b111 3
0:
0'
#74
b1000 *
b11111111111111111111111111111010 )
b11111111111111111111111111111000 *
b1010 "
b1000 #
b10 +
b1000 3
11
02
0=
1'
07
18
19
1:
1=
0'
1<
15
0$
1;
#75
0-
0(
#76
b11111111111111111111111111111001 *
b1001 #
b1 +
b1 .
b1001 3
0:
0=
1'
0&
#78
b11111111111111111111111111111010 *
b1010 #
b0 +
b0 .
b1010 3
09
1:
1=
0'
#80
b11111111111111111111111111111011 *
b1011 #
b11111111111111111111111111111111 +
b1111 .
b1011 3
0:
0=
1'
0<
1&
0;
1%
05
1$
#82
b11111111111111111111111111111100 *
b1100 #
b11111111111111111111111111111110 +
b1110 .
b1100 3
08
19
1:
1=
0'
1<
#84
b11111111111111111111111111111101 *
b1101 #
b11111111111111111111111111111101 +
b1101 .
b1101 3
0:
0=
1'
0&
#86
b11111111111111111111111111111110 *
b1110 #
b11111111111111111111111111111100 +
b1100 .
b1110 3
09
1:
1=
0'
#88
b11111111111111111111111111111111 *
b1111 #
b11111111111111111111111111111011 +
b1011 .
b1111 3
0:
0=
1'
0<
1&
0%
#90
b0 *
b0 #
b11111111111111111111111111111010 +
b1010 .
b0 3
17
18
19
1:
1=
0'
1<
15
1$
1;
#92
b1 *
b1 #
b11111111111111111111111111111001 +
b1001 .
b1 3
0:
0=
1'
0&
#94
b10 *
b10 #
b11111111111111111111111111111000 +
b1000 .
b10 3
09
1:
1=
0'
#96
b11 *
b11 #
b11111111111111111111111111110111 +
b111 .
b11 3
0:
0=
1'
0<
1&
0;
1%
0$
#97
1-
1(
#98
b100 *
b100 #
b11111111111111111111111111110110 +
b110 .
b100 3
08
19
1:
1=
0'
1<
#100
b101 *
b101 #
b11111111111111111111111111110101 +
b101 .
b101 3
0:
0=
1'
0&
#102
b110 *
b110 #
b11111111111111111111111111110100 +
b100 .
b110 3
09
1:
1=
0'
#104
b111 *
b111 #
b11111111111111111111111111110011 +
b11 .
b111 3
0:
0=
1'
0<
1&
0%
#106
b1000 *
b11111111111111111111111111111011 )
b11111111111111111111111111111000 *
b1011 "
b1000 #
b11 +
b1000 3
12
1=
0'
1<
0&
1%
07
18
19
1:
1'
1&
1;
0%
#107
0-
0(
#108
b11111111111111111111111111111001 *
b1001 #
b10 +
b10 .
b1001 3
0:
0'
#110
b11111111111111111111111111111010 *
b1010 #
b1 +
b1 .
b1010 3
09
1:
1'
0&
#112
b11111111111111111111111111111011 *
b1011 #
b0 +
b0 .
b1011 3
0:
0'
#114
b11111111111111111111111111111100 *
b1100 #
b11111111111111111111111111111111 +
b1111 .
b1100 3
08
19
1:
1'
1&
0;
1%
05
1$
#116
b11111111111111111111111111111101 *
b1101 #
b11111111111111111111111111111110 +
b1110 .
b1101 3
0:
0'
#118
b11111111111111111111111111111110 *
b1110 #
b11111111111111111111111111111101 +
b1101 .
b1110 3
09
1:
1'
0&
#120
b11111111111111111111111111111111 *
b1111 #
b11111111111111111111111111111100 +
b1100 .
b1111 3
0:
0'
#122
b0 *
b0 #
b11111111111111111111111111111011 +
b1011 .
b0 3
17
18
19
1:
1'
1&
1;
0%
15
#124
b1 *
b1 #
b11111111111111111111111111111010 +
b1010 .
b1 3
0:
0'
#126
b10 *
b10 #
b11111111111111111111111111111001 +
b1001 .
b10 3
09
1:
1'
0&
#128
b11 *
b11 #
b11111111111111111111111111111000 +
b1000 .
b11 3
0:
0'
#130
b100 *
b100 #
b11111111111111111111111111110111 +
b111 .
b100 3
08
19
1:
1'
1&
0;
1%
0$
#131
1-
1(
#132
b101 *
b101 #
b11111111111111111111111111110110 +
b110 .
b101 3
0:
0'
#134
b110 *
b110 #
b11111111111111111111111111110101 +
b101 .
b110 3
09
1:
1'
0&
#136
b111 *
b111 #
b11111111111111111111111111110100 +
b100 .
b111 3
0:
0'
#138
b1000 *
b11111111111111111111111111111100 )
b11111111111111111111111111111000 *
b1100 "
b1000 #
b100 +
b1000 3
10
01
02
0=
1'
0<
07
18
19
1:
1=
0'
1;
1%
1<
#139
0-
0(
#140
b11111111111111111111111111111001 *
b1001 #
b11 +
b11 .
b1001 3
0:
0=
1'
0<
1&
0%
#142
b11111111111111111111111111111010 *
b1010 #
b10 +
b10 .
b1010 3
09
1:
1=
0'
#144
b11111111111111111111111111111011 *
b1011 #
b1 +
b1 .
b1011 3
0:
0=
1'
0&
#146
b11111111111111111111111111111100 *
b1100 #
b0 +
b0 .
b1100 3
08
19
1:
1=
0'
1;
0%
15
0$
1<
#148
b11111111111111111111111111111101 *
b1101 #
b11111111111111111111111111111111 +
b1111 .
b1101 3
0:
0=
1'
0<
1&
0;
1%
05
1$
#150
b11111111111111111111111111111110 *
b1110 #
b11111111111111111111111111111110 +
b1110 .
b1110 3
09
1:
1=
0'
#152
b11111111111111111111111111111111 *
b1111 #
b11111111111111111111111111111101 +
b1101 .
b1111 3
0:
0=
1'
0&
#154
b0 *
b0 #
b11111111111111111111111111111100 +
b1100 .
b0 3
17
18
19
1:
1=
0'
1;
1%
15
1<
#156
b1 *
b1 #
b11111111111111111111111111111011 +
b1011 .
b1 3
0:
0=
1'
0<
1&
0%
#158
b10 *
b10 #
b11111111111111111111111111111010 +
b1010 .
b10 3
09
1:
1=
0'
#160
b11 *
b11 #
b11111111111111111111111111111001 +
b1001 .
b11 3
0:
0=
1'
0&
#162
b100 *
b100 #
b11111111111111111111111111111000 +
b1000 .
b100 3
08
19
1:
1=
0'
1;
0%
1$
1<
#164
b101 *
b101 #
b11111111111111111111111111110111 +
b111 .
b101 3
0:
0=
1'
0<
1&
0;
1%
0$
#165
1-
1(
#166
b110 *
b110 #
b11111111111111111111111111110110 +
b110 .
b110 3
09
1:
1=
0'
#168
b111 *
b111 #
b11111111111111111111111111110101 +
b101 .
b111 3
0:
0=
1'
0&
#170
b1000 *
b11111111111111111111111111111101 )
b11111111111111111111111111111000 *
b1101 "
b1000 #
b101 +
b1000 3
12
1=
0'
1&
07
18
19
1:
1'
1<
0&
1;
#171
0-
0(
#172
b11111111111111111111111111111001 *
b1001 #
b100 +
b100 .
b1001 3
0:
0'
#174
b11111111111111111111111111111010 *
b1010 #
b11 +
b11 .
b1010 3
09
1:
1'
0<
1&
0%
#176
b11111111111111111111111111111011 *
b1011 #
b10 +
b10 .
b1011 3
0:
0'
#178
b11111111111111111111111111111100 *
b1100 #
b1 +
b1 .
b1100 3
08
19
1:
1'
1<
0&
#180
b11111111111111111111111111111101 *
b1101 #
b0 +
b0 .
b1101 3
0:
0'
#182
b11111111111111111111111111111110 *
b1110 #
b11111111111111111111111111111111 +
b1111 .
b1110 3
09
1:
1'
0<
1&
0;
1%
05
1$
#184
b11111111111111111111111111111111 *
b1111 #
b11111111111111111111111111111110 +
b1110 .
b1111 3
0:
0'
#186
b0 *
b0 #
b11111111111111111111111111111101 +
b1101 .
b0 3
17
18
19
1:
1'
1<
0&
1;
15
#188
b1 *
b1 #
b11111111111111111111111111111100 +
b1100 .
b1 3
0:
0'
#190
b10 *
b10 #
b11111111111111111111111111111011 +
b1011 .
b10 3
09
1:
1'
0<
1&
0%
#192
b11 *
b11 #
b11111111111111111111111111111010 +
b1010 .
b11 3
0:
0'
#194
b100 *
b100 #
b11111111111111111111111111111001 +
b1001 .
b100 3
08
19
1:
1'
1<
0&
#196
b101 *
b101 #
b11111111111111111111111111111000 +
b1000 .
b101 3
0:
0'
#198
b110 *
b110 #
b11111111111111111111111111110111 +
b111 .
b110 3
09
1:
1'
0<
1&
0;
1%
0$
#199
1-
1(
#200
b111 *
b111 #
b11111111111111111111111111110110 +
b110 .
b111 3
0:
0'
#202
b1000 *
b11111111111111111111111111111110 )
b11111111111111111111111111111000 *
b1110 "
b1000 #
b110 +
b1000 3
11
02
0=
1'
07
18
19
1:
1=
0'
1<
1;
#203
0-
0(
#204
b11111111111111111111111111111001 *
b1001 #
b101 +
b101 .
b1001 3
0:
0=
1'
0&
#206
b11111111111111111111111111111010 *
b1010 #
b100 +
b100 .
b1010 3
09
1:
1=
0'
#208
b11111111111111111111111111111011 *
b1011 #
b11 +
b11 .
b1011 3
0:
0=
1'
0<
1&
0%
#210
b11111111111111111111111111111100 *
b1100 #
b10 +
b10 .
b1100 3
08
19
1:
1=
0'
1<
#212
b11111111111111111111111111111101 *
b1101 #
b1 +
b1 .
b1101 3
0:
0=
1'
0&
#214
b11111111111111111111111111111110 *
b1110 #
b0 +
b0 .
b1110 3
09
1:
1=
0'
#216
b11111111111111111111111111111111 *
b1111 #
b11111111111111111111111111111111 +
b1111 .
b1111 3
0:
0=
1'
0<
1&
0;
1%
05
1$
#218
b0 *
b0 #
b11111111111111111111111111111110 +
b1110 .
b0 3
17
18
19
1:
1=
0'
1<
1;
15
#220
b1 *
b1 #
b11111111111111111111111111111101 +
b1101 .
b1 3
0:
0=
1'
0&
#222
b10 *
b10 #
b11111111111111111111111111111100 +
b1100 .
b10 3
09
1:
1=
0'
#224
b11 *
b11 #
b11111111111111111111111111111011 +
b1011 .
b11 3
0:
0=
1'
0<
1&
0%
#226
b100 *
b100 #
b11111111111111111111111111111010 +
b1010 .
b100 3
08
19
1:
1=
0'
1<
#228
b101 *
b101 #
b11111111111111111111111111111001 +
b1001 .
b101 3
0:
0=
1'
0&
#230
b110 *
b110 #
b11111111111111111111111111111000 +
b1000 .
b110 3
09
1:
1=
0'
#232
b111 *
b111 #
b11111111111111111111111111110111 +
b111 .
b111 3
0:
0=
1'
0<
1&
0;
1%
0$
#233
1-
1(
#234
b1000 *
b11111111111111111111111111111111 )
b11111111111111111111111111111000 *
b1111 "
b1000 #
b111 +
b1000 3
12
1=
0'
1<
0&
1;
0%
1$
07
18
19
1:
1'
1&
1%
0$
#235
0-
0(
#236
b11111111111111111111111111111001 *
b1001 #
b110 +
b110 .
b1001 3
0:
0'
#238
b11111111111111111111111111111010 *
b1010 #
b101 +
b101 .
b1010 3
09
1:
1'
0&
#240
b11111111111111111111111111111011 *
b1011 #
b100 +
b100 .
b1011 3
0:
0'
#242
b11111111111111111111111111111100 *
b1100 #
b11 +
b11 .
b1100 3
08
19
1:
1'
1&
0%
#244
b11111111111111111111111111111101 *
b1101 #
b10 +
b10 .
b1101 3
0:
0'
#246
b11111111111111111111111111111110 *
b1110 #
b1 +
b1 .
b1110 3
09
1:
1'
0&
#248
b11111111111111111111111111111111 *
b1111 #
b0 +
b0 .
b1111 3
0:
0'
#250
b0 *
b0 #
b11111111111111111111111111111111 +
b1111 .
b0 3
17
18
19
1:
1'
1&
1%
1$
#252
b1 *
b1 #
b11111111111111111111111111111110 +
b1110 .
b1 3
0:
0'
#254
b10 *
b10 #
b11111111111111111111111111111101 +
b1101 .
b10 3
09
1:
1'
0&
#256
b11 *
b11 #
b11111111111111111111111111111100 +
b1100 .
b11 3
0:
0'
#258
b100 *
b100 #
b11111111111111111111111111111011 +
b1011 .
b100 3
08
19
1:
1'
1&
0%
#260
b101 *
b101 #
b11111111111111111111111111111010 +
b1010 .
b101 3
0:
0'
#262
b110 *
b110 #
b11111111111111111111111111111001 +
b1001 .
b110 3
09
1:
1'
0&
#264
b111 *
b111 #
b11111111111111111111111111111000 +
b1000 .
b111 3
0:
0'
#266
b1000 *
b0 )
b11111111111111111111111111111000 *
b0 "
b1000 #
b1000 +
b1000 3
0/
00
01
02
0=
1'
0<
0;
05
07
18
19
1:
1=
0'
0%
1$
1<
1;
#267
1-
1(
#268
b11111111111111111111111111111001 *
b1001 #
b111 +
b111 .
b1001 3
0:
0=
1'
0<
1&
0;
1%
0$
#269
0-
0(
#270
b11111111111111111111111111111010 *
b1010 #
b110 +
b110 .
b1010 3
09
1:
1=
0'
#272
b11111111111111111111111111111011 *
b1011 #
b101 +
b101 .
b1011 3
0:
0=
1'
0&
#274
b11111111111111111111111111111100 *
b1100 #
b100 +
b100 .
b1100 3
08
19
1:
1=
0'
1%
1<
#276
b11111111111111111111111111111101 *
b1101 #
b11 +
b11 .
b1101 3
0:
0=
1'
0<
1&
0%
#278
b11111111111111111111111111111110 *
b1110 #
b10 +
b10 .
b1110 3
09
1:
1=
0'
#280
b11111111111111111111111111111111 *
b1111 #
b1 +
b1 .
b1111 3
0:
0=
1'
0&
#282
b0 *
b0 #
b0 +
b0 .
b0 3
17
18
19
1:
1=
0'
0%
0$
1<
1;
15
#284
b1 *
b1 #
b11111111111111111111111111111111 +
b1111 .
b1 3
0:
0=
1'
0<
1&
0;
1%
05
1$
#286
b10 *
b10 #
b11111111111111111111111111111110 +
b1110 .
b10 3
09
1:
1=
0'
#288
b11 *
b11 #
b11111111111111111111111111111101 +
b1101 .
b11 3
0:
0=
1'
0&
#290
b100 *
b100 #
b11111111111111111111111111111100 +
b1100 .
b100 3
08
19
1:
1=
0'
1%
1<
#292
b101 *
b101 #
b11111111111111111111111111111011 +
b1011 .
b101 3
0:
0=
1'
0<
1&
0%
#294
b110 *
b110 #
b11111111111111111111111111111010 +
b1010 .
b110 3
09
1:
1=
0'
#296
b111 *
b111 #
b11111111111111111111111111111001 +
b1001 .
b111 3
0:
0=
1'
0&
#298
b1000 *
b1 )
b11111111111111111111111111111000 *
b1 "
b1000 #
b1001 +
b1000 3
12
1=
0'
1&
07
18
19
1:
1'
1<
0&
1$
1;
#299
1-
1(
#300
b11111111111111111111111111111001 *
b1001 #
b1000 +
b1000 .
b1001 3
0:
0'
#302
b11111111111111111111111111111010 *
b1010 #
b111 +
b111 .
b1010 3
09
1:
1'
0<
1&
0;
1%
0$
#303
0-
0(
#304
b11111111111111111111111111111011 *
b1011 #
b110 +
b110 .
b1011 3
0:
0'
#306
b11111111111111111111111111111100 *
b1100 #
b101 +
b101 .
b1100 3
08
19
1:
1'
1<
0&
#308
b11111111111111111111111111111101 *
b1101 #
b100 +
b100 .
b1101 3
0:
0'
#310
b11111111111111111111111111111110 *
b1110 #
b11 +
b11 .
b1110 3
09
1:
1'
0<
1&
0%
#312
b11111111111111111111111111111111 *
b1111 #
b10 +
b10 .
b1111 3
0:
0'
#314
b0 *
b0 #
b1 +
b1 .
b0 3
17
18
19
1:
1'
1<
0&
0$
1;
15
#316
b1 *
b1 #
b0 +
b0 .
b1 3
0:
0'
#318
b10 *
b10 #
b11111111111111111111111111111111 +
b1111 .
b10 3
09
1:
1'
0<
1&
0;
1%
05
1$
#320
b11 *
b11 #
b11111111111111111111111111111110 +
b1110 .
b11 3
0:
0'
#322
b100 *
b100 #
b11111111111111111111111111111101 +
b1101 .
b100 3
08
19
1:
1'
1<
0&
#324
b101 *
b101 #
b11111111111111111111111111111100 +
b1100 .
b101 3
0:
0'
#326
b110 *
b110 #
b11111111111111111111111111111011 +
b1011 .
b110 3
09
1:
1'
0<
1&
0%
#328
b111 *
b111 #
b11111111111111111111111111111010 +
b1010 .
b111 3
0:
0'
#330
b1000 *
b10 )
b11111111111111111111111111111000 *
b10 "
b1000 #
b1010 +
b1000 3
11
02
0=
1'
07
18
19
1:
1=
0'
1<
1$
1;
#331
1-
1(
#332
b11111111111111111111111111111001 *
b1001 #
b1001 +
b1001 .
b1001 3
0:
0=
1'
0&
#334
b11111111111111111111111111111010 *
b1010 #
b1000 +
b1000 .
b1010 3
09
1:
1=
0'
#336
b11111111111111111111111111111011 *
b1011 #
b111 +
b111 .
b1011 3
0:
0=
1'
0<
1&
0;
1%
0$
#337
0-
0(
#338
b11111111111111111111111111111100 *
b1100 #
b110 +
b110 .
b1100 3
08
19
1:
1=
0'
1<
#340
b11111111111111111111111111111101 *
b1101 #
b101 +
b101 .
b1101 3
0:
0=
1'
0&
#342
b11111111111111111111111111111110 *
b1110 #
b100 +
b100 .
b1110 3
09
1:
1=
0'
#344
b11111111111111111111111111111111 *
b1111 #
b11 +
b11 .
b1111 3
0:
0=
1'
0<
1&
0%
#346
b0 *
b0 #
b10 +
b10 .
b0 3
17
18
19
1:
1=
0'
1<
0$
1;
15
#348
b1 *
b1 #
b1 +
b1 .
b1 3
0:
0=
1'
0&
#350
b10 *
b10 #
b0 +
b0 .
b10 3
09
1:
1=
0'
#352
b11 *
b11 #
b11111111111111111111111111111111 +
b1111 .
b11 3
0:
0=
1'
0<
1&
0;
1%
05
1$
#354
b100 *
b100 #
b11111111111111111111111111111110 +
b1110 .
b100 3
08
19
1:
1=
0'
1<
#356
b101 *
b101 #
b11111111111111111111111111111101 +
b1101 .
b101 3
0:
0=
1'
0&
#358
b110 *
b110 #
b11111111111111111111111111111100 +
b1100 .
b110 3
09
1:
1=
0'
#360
b111 *
b111 #
b11111111111111111111111111111011 +
b1011 .
b111 3
0:
0=
1'
0<
1&
0%
#362
b1000 *
b11 )
b11111111111111111111111111111000 *
b11 "
b1000 #
b1011 +
b1000 3
12
1=
0'
1<
0&
1%
07
18
19
1:
1'
1&
1;
0%
#363
1-
1(
#364
b11111111111111111111111111111001 *
b1001 #
b1010 +
b1010 .
b1001 3
0:
0'
#366
b11111111111111111111111111111010 *
b1010 #
b1001 +
b1001 .
b1010 3
09
1:
1'
0&
#368
b11111111111111111111111111111011 *
b1011 #
b1000 +
b1000 .
b1011 3
0:
0'
#370
b11111111111111111111111111111100 *
b1100 #
b111 +
b111 .
b1100 3
08
19
1:
1'
1&
0;
1%
0$
#371
0-
0(
#372
b11111111111111111111111111111101 *
b1101 #
b110 +
b110 .
b1101 3
0:
0'
#374
b11111111111111111111111111111110 *
b1110 #
b101 +
b101 .
b1110 3
09
1:
1'
0&
#376
b11111111111111111111111111111111 *
b1111 #
b100 +
b100 .
b1111 3
0:
0'
#378
b0 *
b0 #
b11 +
b11 .
b0 3
17
18
19
1:
1'
1&
1;
0%
15
#380
b1 *
b1 #
b10 +
b10 .
b1 3
0:
0'
#382
b10 *
b10 #
b1 +
b1 .
b10 3
09
1:
1'
0&
#384
b11 *
b11 #
b0 +
b0 .
b11 3
0:
0'
#386
b100 *
b100 #
b11111111111111111111111111111111 +
b1111 .
b100 3
08
19
1:
1'
1&
0;
1%
05
1$
#388
b101 *
b101 #
b11111111111111111111111111111110 +
b1110 .
b101 3
0:
0'
#390
b110 *
b110 #
b11111111111111111111111111111101 +
b1101 .
b110 3
09
1:
1'
0&
#392
b111 *
b111 #
b11111111111111111111111111111100 +
b1100 .
b111 3
0:
0'
#394
b1000 *
b100 )
b11111111111111111111111111111000 *
b100 "
b1000 #
b1100 +
b1000 3
10
01
02
0=
1'
0<
07
18
19
1:
1=
0'
1;
1%
1<
#395
1-
1(
#396
b11111111111111111111111111111001 *
b1001 #
b1011 +
b1011 .
b1001 3
0:
0=
1'
0<
1&
0%
#398
b11111111111111111111111111111010 *
b1010 #
b1010 +
b1010 .
b1010 3
09
1:
1=
0'
#400
b11111111111111111111111111111011 *
b1011 #
b1001 +
b1001 .
b1011 3
0:
0=
1'
0&
#402
b11111111111111111111111111111100 *
b1100 #
b1000 +
b1000 .
b1100 3
08
19
1:
1=
0'
1;
0%
1$
1<
#404
b11111111111111111111111111111101 *
b1101 #
b111 +
b111 .
b1101 3
0:
0=
1'
0<
1&
0;
1%
0$
#405
0-
0(
#406
b11111111111111111111111111111110 *
b1110 #
b110 +
b110 .
b1110 3
09
1:
1=
0'
#408
b11111111111111111111111111111111 *
b1111 #
b101 +
b101 .
b1111 3
0:
0=
1'
0&
#410
b0 *
b0 #
b100 +
b100 .
b0 3
17
18
19
1:
1=
0'
1;
1%
15
1<
#412
b1 *
b1 #
b11 +
b11 .
b1 3
0:
0=
1'
0<
1&
0%
#414
b10 *
b10 #
b10 +
b10 .
b10 3
09
1:
1=
0'
#416
b11 *
b11 #
b1 +
b1 .
b11 3
0:
0=
1'
0&
#418
b100 *
b100 #
b0 +
b0 .
b100 3
08
19
1:
1=
0'
1;
0%
15
0$
1<
#420
b101 *
b101 #
b11111111111111111111111111111111 +
b1111 .
b101 3
0:
0=
1'
0<
1&
0;
1%
05
1$
#422
b110 *
b110 #
b11111111111111111111111111111110 +
b1110 .
b110 3
09
1:
1=
0'
#424
b111 *
b111 #
b11111111111111111111111111111101 +
b1101 .
b111 3
0:
0=
1'
0&
#426
b1000 *
b101 )
b11111111111111111111111111111000 *
b101 "
b1000 #
b1101 +
b1000 3
12
1=
0'
1&
07
18
19
1:
1'
1<
0&
1;
#427
1-
1(
#428
b11111111111111111111111111111001 *
b1001 #
b1100 +
b1100 .
b1001 3
0:
0'
