lab3/ex3/fulladder.v
module fulladder(a, b, ci, sum, co);
  input   a, b, ci;
  output  sum, co;

  assign sum = a^b^ci;
  assign co = (a&b) | (a&ci) | (b&ci);
endmodule

lab3/ex3/fulladder_tb.v
module main;

reg a, b, ci, correct, loop_skipped;
wire sum, co;
integer ai, bi, cii;
fulladder uut(a, b, ci, sum, co);

initial begin
correct = 1; loop_skipped= 1;
$dumpfile("waves.vcd");
$dumpvars;
#1
for( ai=0; ai<=1; ai=ai+1 ) begin
  for( bi=0; bi<=1; bi=bi+1 ) begin
    for( cii=0; cii<=1; cii=cii+1 ) begin
      loop_skipped= 0;
      a = ai[0]; b = bi[0]; ci = cii[0];
      #5 correct = correct & (a + b + ci == {co,sum});
    end
  end
end

if (correct && ~loop_skipped)
  $display("Test Passed -%m");
else
  $display("Test Failed -%m");
$finish;
end

endmodule

lab3/ex3/waves.vcd
$date
    Apr 11, 2018  15:04:43
$end
$version
    TOOL:	ncsim(64)	14.10-s021
$end
$timescale
    1 ns
$end

$scope module main $end
$var reg       1 !    a  $end
$var reg       1 "    b  $end
$var reg       1 #    ci  $end
$var reg       1 $    correct  $end
$var reg       1 %    loop_skipped  $end
$var wire      1 &    sum  $end
$var wire      1 '    co  $end
$var integer  32 (    ai  $end
$var integer  32 )    bi  $end
$var integer  32 *    cii  $end

$scope module uut $end
$var wire      1 +    a  $end
$var wire      1 ,    b  $end
$var wire      1 -    ci  $end
$var wire      1 &    sum  $end
$var wire      1 '    co  $end
$upscope $end

$upscope $end

$enddefinitions $end
$dumpvars
x!
x"
x#
1$
1%
x&
x'
bx (
bx )
bx *
x+
x,
x-
$end
#1
b0 (
b0 )
b0 *
0%
0!
0"
0#
0-
0,
0+
0&
0'
#6
b1 *
1#
1-
1&
#11
b10 *
b1 )
b0 *
1"
0#
0-
1,
#16
b1 *
1#
1-
1'
0&
#21
b10 *
b10 )
b1 (
b0 )
b0 *
1!
0"
0#
0-
0,
1+
0'
1&
#26
b1 *
1#
1-
1'
0&
#31
b10 *
b1 )
b0 *
1"
0#
0-
1,
#36
b1 *
1#
1-
1&
#41
b10 *
b10 )
b10 (
